inventree_template_fix/__init__.py
inventree_template_fix/fix_plugin.py
inventree_template_fix/version.py
inventree_template_fix-0.1.1.dist-info/LICENSE
inventree_template_fix-0.1.1.dist-info/METADATA
inventree_template_fix-0.1.1.dist-info/WHEEL
inventree_template_fix-0.1.1.dist-info/entry_points.txt
inventree_template_fix-0.1.1.dist-info/top_level.txt
inventree_template_fix-0.1.1.dist-info/RECORD
