Metadata-Version: 2.1
Name: inventree-template-fix
Version: 0.1.1
Summary: Retroactively apply parameters to Parts that were added before a category template was created
Home-page: https://github.com/MrARM/inventree-template-fix
Author: Jordan Bush
Author-email: jordan@bush.ax
License: MIT
Keywords: inventree template fix
Requires-Python: >=3.6
License-File: LICENSE
